nonebot_plugin_paminet_nodirtymsg/__init__.py
nonebot_plugin_paminet_nodirtymsg/config.py
nonebot_plugin_paminet_nodirtymsg/filter.py
nonebot_plugin_paminet_nodirtymsg/handler.py
nonebot_plugin_paminet_nodirtymsg/loader.py
nonebot_plugin_paminet_nodirtymsg/data/badwords.json
nonebot_plugin_paminet_nodirtymsg-0.3.10.dist-info/LICENSE
nonebot_plugin_paminet_nodirtymsg-0.3.10.dist-info/METADATA
nonebot_plugin_paminet_nodirtymsg-0.3.10.dist-info/WHEEL
nonebot_plugin_paminet_nodirtymsg-0.3.10.dist-info/entry_points.txt
nonebot_plugin_paminet_nodirtymsg-0.3.10.dist-info/top_level.txt
nonebot_plugin_paminet_nodirtymsg-0.3.10.dist-info/RECORD
