Metadata-Version: 2.2
Name: nonebot-plugin-paminet-nodirtymsg
Version: 0.3.10
Summary: 基于Trie树的高效群聊违禁词过滤插件,自动撤回群成员的敏感发言.需要管理员权限.
Author-email: Mipa <shcdwrzh@outlook.com>
License: MIT
Project-URL: Homepage, https://github.com/PamiNET-Corp/nonebot-plugin-paminet-nodirtymsg
Project-URL: Repository, https://github.com/PamiNET-Corp/nonebot-plugin-paminet-nodirtymsg
Project-URL: Documentation, https://github.com/PamiNET-Corp/nonebot-plugin-paminet-nodirtymsg#readme
Project-URL: Issues, https://github.com/PamiNET-Corp/nonebot-plugin-paminet-nodirtymsg/issues
Keywords: nonebot,chat,moderation,filter
Classifier: Development Status :: 4 - Beta
Classifier: Intended Audience :: Developers
Classifier: License :: OSI Approved :: MIT License
Classifier: Programming Language :: Python :: 3.8
Classifier: Programming Language :: Python :: 3.9
Classifier: Programming Language :: Python :: 3.10
Classifier: Programming Language :: Python :: 3.11
Classifier: Topic :: Communications :: Chat
Classifier: Topic :: Software Development :: Libraries :: Python Modules
Requires-Python: >=3.8
License-File: LICENSE
Requires-Dist: nonebot2>=2.3.0
Requires-Dist: nonebot-adapter-onebot>=2.0.0
Requires-Dist: nonebot-plugin-localstore>=0.7.0
Requires-Dist: aiofiles>=23.1.0
